test_pypi_abc/__init__.py
test_pypi_abc/flash.py
test_pypi_abc/ring.py
test_pypi_czs-0.0.3.dist-info/METADATA
test_pypi_czs-0.0.3.dist-info/WHEEL
test_pypi_czs-0.0.3.dist-info/entry_points.txt
test_pypi_czs-0.0.3.dist-info/licenses/LICENSE
test_pypi_czs-0.0.3.dist-info/RECORD
