Metadata-Version: 2.1
Name: test_pypi_czs
Version: 0.0.3
Summary: A small example package
Author: Hang Zhang
Author-Email: Zesen Cheng <ross@huggingface.co>
License: MIT
Classifier: Development Status :: 4 - Beta
Classifier: Intended Audience :: Education
Classifier: Intended Audience :: Science/Research
Classifier: License :: OSI Approved :: MIT License
Classifier: Programming Language :: Python :: 3.8
Classifier: Programming Language :: Python :: 3.9
Classifier: Programming Language :: Python :: 3.10
Classifier: Programming Language :: Python :: 3.11
Classifier: Programming Language :: Python :: 3.12
Classifier: Topic :: Scientific/Engineering
Classifier: Topic :: Scientific/Engineering :: Artificial Intelligence
Classifier: Topic :: Software Development
Classifier: Topic :: Software Development :: Libraries
Classifier: Topic :: Software Development :: Libraries :: Python Modules
Project-URL: Homepage, https://github.com/clownrat6/test_pypi_czs
Project-URL: Issues, https://github.com/clownrat6/test_pypi_czs/issues
Requires-Python: >=3.8
Requires-Dist: torch>=2.0.0
Requires-Dist: numpy
Requires-Dist: triton>=2.2.0
